vislib/__init__.py
vislib/taucharts.py
vislib/treant.py
vislib/visjs.py
vislib-0.2.dist-info/METADATA
vislib-0.2.dist-info/RECORD
vislib-0.2.dist-info/WHEEL
vislib-0.2.dist-info/top_level.txt
