Metadata-Version: 2.1
Name: vislib
Version: 0.2
Summary: Reusable html-based python visualization library
Home-page: https://github.com/mshafir/vislib
Author: Michael Shafir
Author-email: michael.shafir@gmail.com
License: MIT
Platform: UNKNOWN
Classifier: Programming Language :: Python
Classifier: License :: OSI Approved :: MIT License
Classifier: Operating System :: OS Independent
Classifier: Framework :: IPython
Requires-Dist: ipython
Requires-Dist: Jinja2
